common_util/HTMLTestRunner.py
common_util/__init__.py
common_util/base_tool.py
common_util/db_manage.py
common_util/endecrypt.py
common_util/file_handler.py
common_util/ssh_util.py
oneSports_TestCommon-2.1.7.dist-info/METADATA
oneSports_TestCommon-2.1.7.dist-info/WHEEL
oneSports_TestCommon-2.1.7.dist-info/top_level.txt
oneSports_TestCommon-2.1.7.dist-info/RECORD
